<?xml version="1.0" encoding="UTF-8"?>

<suite name="Suite">
	<test name="Test">
		<classes>
			<class name="com.intense.testcases.OpenBrowserTestcase" />
			<class name="com.intense.testcases.LoginTestcase" />
			<class name="com.intense.testcases.UserManagerTestcase" />
			<class name="com.intense.testcases.UsersTestcase" />
			<!--<class name="com.intense.testcases.CreateUserTestcase"/> -->
			
			<class name="com.intense.testcases.CreateUserTestcase">
				<methods>
					<exclude name="createUserOption"></exclude> -->
					<include name="frameMove"></include> 
					<exclude name="createNewUserData"></exclude>
					<exclude name="saveCreateUsrDataOptions"></exclude>
								</methods>
				</class>
			<class name="com.intense.testcases.SearchUserTestcase" />
			<class name="com.intense.testcases.EditUserTestcase" />
			<class name="com.intense.testcases.LogoutTestcase" />
		</classes>
	</test>
</suite> 

